Metadata-Version: 2.1
Name: pupdb
Version: 0.1.4
Summary: A simple file-based key-value database written in Python.
Home-page: https://github.com/tuxmonk/pupdb
Author: tuxmonk
Author-email: 30048080+tuxmonk@users.noreply.github.com
License: MIT
Download-URL: https://github.com/tuxmonk/pupdb/archive/master.zip
Keywords: file-based,key-value-store,python,database,rest-api,process-safe,cross-language
Platform: UNKNOWN
Classifier: Development Status :: 4 - Beta
Classifier: Intended Audience :: Developers
Classifier: Topic :: Software Development :: Build Tools
Classifier: License :: OSI Approved :: MIT License
Classifier: Programming Language :: Python :: 2.7
Classifier: Programming Language :: Python :: 3.4
Classifier: Programming Language :: Python :: 3.5
Classifier: Programming Language :: Python :: 3.6
Classifier: Programming Language :: Python :: 3.7
Classifier: Programming Language :: Python :: 3.8
